README.rst
setup.py
httpcli/__init__.py
httpcli/cli.py
httpcli/client.py
httpcli/content.py
httpcli/core.py
httpcli/output.py
httpcli.egg-info/PKG-INFO
httpcli.egg-info/SOURCES.txt
httpcli.egg-info/dependency_links.txt
httpcli.egg-info/entry_points.txt
httpcli.egg-info/pbr.json
httpcli.egg-info/requires.txt
httpcli.egg-info/top_level.txt