Metadata-Version: 1.1
Name: httpcli
Version: 1.3.0
Summary: RESTful command line HTTP client (and simpler than cURL).
Home-page: http://github.com/dolph/httpcli
Author: Dolph Mathews
Author-email: dolph.mathews@gmail.com
License: UNKNOWN
Keywords: http client cli curl rest restful
Platform: UNKNOWN
Classifier: Development Status :: 4 - Beta
Classifier: Environment :: Console
Classifier: Intended Audience :: Developers
Classifier: Intended Audience :: System Administrators
Classifier: Topic :: Internet :: WWW/HTTP
Classifier: Topic :: Utilities
